codat_sync_for_commerce/__init__.py
codat_sync_for_commerce/_hooks/__init__.py
codat_sync_for_commerce/_hooks/registration.py
codat_sync_for_commerce/_hooks/sdkhooks.py
codat_sync_for_commerce/_hooks/types.py
codat_sync_for_commerce/_version.py
codat_sync_for_commerce/advanced_controls.py
codat_sync_for_commerce/basesdk.py
codat_sync_for_commerce/connections.py
codat_sync_for_commerce/httpclient.py
codat_sync_for_commerce/integrations.py
codat_sync_for_commerce/models/errors/__init__.py
codat_sync_for_commerce/models/errors/errormessage.py
codat_sync_for_commerce/models/errors/sdkerror.py
codat_sync_for_commerce/models/operations/__init__.py
codat_sync_for_commerce/models/operations/create_connection.py
codat_sync_for_commerce/models/operations/get_config_text_sync_flow.py
codat_sync_for_commerce/models/operations/get_configuration.py
codat_sync_for_commerce/models/operations/get_integration_branding.py
codat_sync_for_commerce/models/operations/get_last_successful_sync.py
codat_sync_for_commerce/models/operations/get_latest_sync.py
codat_sync_for_commerce/models/operations/get_sync_by_id.py
codat_sync_for_commerce/models/operations/get_sync_flow_url.py
codat_sync_for_commerce/models/operations/get_sync_status.py
codat_sync_for_commerce/models/operations/get_visible_accounts.py
codat_sync_for_commerce/models/operations/list_companies.py
codat_sync_for_commerce/models/operations/list_connections.py
codat_sync_for_commerce/models/operations/list_integrations.py
codat_sync_for_commerce/models/operations/list_syncs.py
codat_sync_for_commerce/models/operations/request_sync.py
codat_sync_for_commerce/models/operations/request_sync_for_date_range.py
codat_sync_for_commerce/models/operations/set_configuration.py
codat_sync_for_commerce/models/operations/update_config_text_sync_flow.py
codat_sync_for_commerce/models/operations/update_connection.py
codat_sync_for_commerce/models/operations/update_connection_authorization.py
codat_sync_for_commerce-6.1.0.dist-info/METADATA
codat_sync_for_commerce-6.1.0.dist-info/WHEEL
codat_sync_for_commerce-6.1.0.dist-info/RECORD
