Metadata-Version: 2.3
Name: codat-sync-for-commerce
Version: 6.1.0
Summary: Push merchants' data from your ecommerce or point-of-sale (POS) platform into your merchants' accounting software.
Author: Speakeasy
Requires-Python: >=3.9
Classifier: Programming Language :: Python :: 3
Classifier: Programming Language :: Python :: 3.9
Classifier: Programming Language :: Python :: 3.10
Classifier: Programming Language :: Python :: 3.11
Classifier: Programming Language :: Python :: 3.12
Classifier: Programming Language :: Python :: 3.13
Requires-Dist: eval-type-backport (>=0.2.0)
Requires-Dist: httpx (>=0.28.1)
Requires-Dist: pydantic (>=2.10.3)
Requires-Dist: python-dateutil (>=2.8.2)
Requires-Dist: typing-inspect (>=0.9.0)
Project-URL: Repository, https://github.com/codatio/client-sdk-python.git
